tbank_kassa_api/__init__.py
tbank_kassa_api/enums.py
tbank_kassa_api/funcs.py
tbank_kassa_api/response_models.py
tbank_kassa_api/send_models.py
tbank_kassa_api/tbank_client.py
tbank_kassa_api/tbank_models.py
tbank_kassa_api/tests.py
tbank_kassa_api-0.0.2.7.6.dist-info/LICENSE
tbank_kassa_api-0.0.2.7.6.dist-info/METADATA
tbank_kassa_api-0.0.2.7.6.dist-info/WHEEL
tbank_kassa_api-0.0.2.7.6.dist-info/top_level.txt
tbank_kassa_api-0.0.2.7.6.dist-info/RECORD
