Metadata-Version: 2.1
Name: tbank_kassa_api
Version: 0.0.2.7.6
Author-email: "Evgeny (Krymmy) Momotov" <evgeny.momotov@gmail.com>
License: MIT License. See LICENSE file
Project-URL: Repository, https://github.com/KrymmyEM/tbank_kassa_api
Project-URL: Download, https://github.com/KrymmyEM/tbank_kassa_api/archive/main.zip
Classifier: License :: OSI Approved :: MIT License
Classifier: Operating System :: OS Independent
Classifier: Intended Audience :: End Users/Desktop
Classifier: Intended Audience :: Developers
Classifier: Programming Language :: Python :: 3
Classifier: Programming Language :: Python :: 3.11
Classifier: Programming Language :: Python :: Implementation :: PyPy
Classifier: Programming Language :: Python :: Implementation :: CPython
License-File: LICENSE
Requires-Dist: aiohttp <=3.10.5
Requires-Dist: pydantic ==2.8.2
Requires-Dist: requests <=2.32.3
